slivka_client/__init__.py
slivka_client/__main__.py
slivka_client/client.py
slivka_client/file.py
slivka_client/job.py
slivka_client/nb_utils.py
slivka_client/service.py
slivka_client-1.2.1b1.dist-info/LICENSE
slivka_client-1.2.1b1.dist-info/METADATA
slivka_client-1.2.1b1.dist-info/WHEEL
slivka_client-1.2.1b1.dist-info/entry_points.txt
slivka_client-1.2.1b1.dist-info/top_level.txt
slivka_client-1.2.1b1.dist-info/RECORD
