Metadata-Version: 2.1
Name: slivka-client
Version: 1.2.1b1
Summary: A Python client for Slivka services
Home-page: https://github.com/bartongroup/slivka-python-client
Author: Mateusz Warowny
Author-email: m.m.z.warowny@dundee.ac.uk
Maintainer: Stuart MacGowan
Maintainer-email: smacgowan@dundee.ac.uk
Project-URL: Documentation, https://github.com/bartongroup/slivka-python-client#readme
Project-URL: Source, https://github.com/bartongroup/slivka-python-client
Project-URL: Tracker, https://github.com/bartongroup/slivka-python-client/issues
Project-URL: Organization, https://www.compbio.dundee.ac.uk/drsasp.html
Keywords: slivka,client,bioinformatics,computational biology,REST API
Classifier: Development Status :: 4 - Beta
Classifier: Intended Audience :: Science/Research
Classifier: Topic :: Scientific/Engineering :: Bio-Informatics
Classifier: Programming Language :: Python :: 3
Classifier: License :: OSI Approved :: Apache Software License
Classifier: Operating System :: OS Independent
Requires-Python: >=3.6
License-File: LICENSE
Requires-Dist: attrs>=19.3
Requires-Dist: click>=7.0
Requires-Dist: requests>=2.13.0
